COPYING
MANIFEST.in
setup.cfg
setup.py
src/authentic2_idp_freshdesk/__init__.py
src/authentic2_idp_freshdesk/app_settings.py
src/authentic2_idp_freshdesk/models.py
src/authentic2_idp_freshdesk/tests.py
src/authentic2_idp_freshdesk/urls.py
src/authentic2_idp_freshdesk/views.py
src/authentic2_idp_freshdesk.egg-info/PKG-INFO
src/authentic2_idp_freshdesk.egg-info/SOURCES.txt
src/authentic2_idp_freshdesk.egg-info/dependency_links.txt
src/authentic2_idp_freshdesk.egg-info/entry_points.txt
src/authentic2_idp_freshdesk.egg-info/top_level.txt