Metadata-Version: 1.0
Name: authentic2-idp-freshdesk
Version: 0.2
Summary: Freshdesk simple SSO support for Authentic2
Home-page: UNKNOWN
Author: Jocelyn Delalande
Author-email: jdelalande@oasiswork.fr
License: AGPLv3
Platform: UNKNOWN
